{"date": "2025-07-16", "nav_total": 3984435374, "units": 346709000, "nav_per_unit": 11.49, "n_holdings": 50, "holdings": [{"code": "2330", "name": "台積電", "shares": 323000, "amount": 364990000, "weight": 9.16}, {"code": "3017", "name": "奇鋐", "shares": 243000, "amount": 206064000, "weight": 5.17}, {"code": "2308", "name": "台達電", "shares": 363000, "amount": 181500000, "weight": 4.56}, {"code": "6223", "name": "旺矽", "shares": 155000, "amount": 173600000, "weight": 4.36}, {"code": "3665", "name": "貿聯-KY", "shares": 187000, "amount": 164934000, "weight": 4.14}, {"code": "3231", "name": "緯創", "shares": 1317000, "amount": 155406000, "weight": 3.9}, {"code": "3661", "name": "世芯-KY", "shares": 43000, "amount": 154800000, "weight": 3.89}, {"code": "3653", "name": "健策", "shares": 99000, "amount": 147015000, "weight": 3.69}, {"code": "8210", "name": "勤誠", "shares": 275000, "amount": 146850000, "weight": 3.69}, {"code": "2382", "name": "廣達", "shares": 530000, "amount": 144425000, "weight": 3.62}, {"code": "2368", "name": "金像電", "shares": 442000, "amount": 140335000, "weight": 3.52}, {"code": "2345", "name": "智邦", "shares": 148000, "amount": 113812000, "weight": 2.86}, {"code": "2317", "name": "鴻海", "shares": 696000, "amount": 113100000, "weight": 2.84}, {"code": "6669", "name": "緯穎", "shares": 45000, "amount": 112725000, "weight": 2.83}, {"code": "2454", "name": "聯發科", "shares": 79000, "amount": 111390000, "weight": 2.8}, {"code": "2383", "name": "台光電", "shares": 112000, "amount": 110096000, "weight": 2.76}, {"code": "2891", "name": "中信金", "shares": 2467000, "amount": 106081000, "weight": 2.66}, {"code": "6139", "name": "亞翔", "shares": 307000, "amount": 98854000, "weight": 2.48}, {"code": "3533", "name": "嘉澤", "shares": 64000, "amount": 91840000, "weight": 2.3}, {"code": "3264", "name": "欣銓", "shares": 1094000, "amount": 81721800, "weight": 2.05}, {"code": "3008", "name": "大立光", "shares": 25000, "amount": 57500000, "weight": 1.44}, {"code": "2059", "name": "川湖", "shares": 25000, "amount": 54625000, "weight": 1.37}, {"code": "3706", "name": "神達", "shares": 802000, "amount": 53974600, "weight": 1.35}, {"code": "6472", "name": "保瑞", "shares": 59000, "amount": 48498000, "weight": 1.22}, {"code": "1210", "name": "大成", "shares": 754000, "amount": 47200400, "weight": 1.18}, {"code": "2327", "name": "國巨", "shares": 84000, "amount": 42168000, "weight": 1.06}, {"code": "8046", "name": "南電", "shares": 241000, "amount": 41693000, "weight": 1.05}, {"code": "6143", "name": "振曜", "shares": 343000, "amount": 39273500, "weight": 0.99}, {"code": "3217", "name": "優群", "shares": 240000, "amount": 37320000, "weight": 0.94}, {"code": "6510", "name": "精測", "shares": 40000, "amount": 35320000, "weight": 0.89}, {"code": "6278", "name": "台表科", "shares": 281000, "amount": 29645500, "weight": 0.74}, {"code": "2609", "name": "陽明", "shares": 455000, "amount": 28983500, "weight": 0.73}, {"code": "5274", "name": "信驊", "shares": 6000, "amount": 29160000, "weight": 0.73}, {"code": "1560", "name": "中砂", "shares": 68000, "amount": 23834000, "weight": 0.6}, {"code": "8069", "name": "元太", "shares": 104000, "amount": 23140000, "weight": 0.58}, {"code": "3605", "name": "宏致", "shares": 334000, "amount": 20173600, "weight": 0.51}, {"code": "6757", "name": "台灣虎航", "shares": 192000, "amount": 16684800, "weight": 0.42}, {"code": "2618", "name": "長榮航", "shares": 430000, "amount": 16555000, "weight": 0.42}, {"code": "3042", "name": "晶技", "shares": 179000, "amount": 15197100, "weight": 0.38}, {"code": "6138", "name": "茂達", "shares": 61000, "amount": 11132500, "weight": 0.28}, {"code": "2439", "name": "美律", "shares": 62000, "amount": 7161000, "weight": 0.18}, {"code": "2886", "name": "兆豐金", "shares": 133000, "amount": 5612600, "weight": 0.14}, {"code": "3045", "name": "台灣大", "shares": 43000, "amount": 4579500, "weight": 0.11}, {"code": "2357", "name": "華碩", "shares": 1000, "amount": 635000, "weight": 0.02}, {"code": "2404", "name": "漢唐", "shares": 1000, "amount": 725000, "weight": 0.02}, {"code": "3044", "name": "健鼎", "shares": 1000, "amount": 240000, "weight": 0.01}, {"code": "2379", "name": "瑞昱", "shares": 1000, "amount": 581000, "weight": 0.01}, {"code": "6274", "name": "台燿", "shares": 1000, "amount": 260000, "weight": 0.01}, {"code": "3376", "name": "新日興", "shares": 1000, "amount": 207500, "weight": 0.01}, {"code": "2884", "name": "玉山金", "shares": 1000, "amount": 35250, "weight": 0.0}]}