{"date": "2025-07-02", "nav_total": 3679031115, "units": 335436000, "nav_per_unit": 10.97, "n_holdings": 44, "holdings": [{"code": "2330", "name": "台積電", "shares": 305000, "amount": 330921490, "weight": 8.9948}, {"code": "3017", "name": "奇鋐", "shares": 209000, "amount": 158628784, "weight": 4.3117}, {"code": "3231", "name": "緯創", "shares": 1299000, "amount": 155876869, "weight": 4.2369}, {"code": "2317", "name": "鴻海", "shares": 867000, "amount": 140450691, "weight": 3.8176}, {"code": "2449", "name": "京元電子", "shares": 1167000, "amount": 120782591, "weight": 3.283}, {"code": "2609", "name": "陽明", "shares": 1628000, "amount": 119005619, "weight": 3.2347}, {"code": "8210", "name": "勤誠", "shares": 235000, "amount": 116205876, "weight": 3.1586}, {"code": "6805", "name": "富世達", "shares": 138000, "amount": 109984635, "weight": 2.9895}, {"code": "8028", "name": "昇陽半導體", "shares": 788000, "amount": 108741122, "weight": 2.9557}, {"code": "2891", "name": "中信金", "shares": 2392000, "amount": 105006906, "weight": 2.8542}, {"code": "5274", "name": "信驊", "shares": 20000, "amount": 99598730, "weight": 2.7072}, {"code": "2382", "name": "廣達", "shares": 330000, "amount": 93057413, "weight": 2.5294}, {"code": "6177", "name": "達麗", "shares": 1907000, "amount": 92774127, "weight": 2.5217}, {"code": "3665", "name": "貿聯-KY", "shares": 111000, "amount": 92682151, "weight": 2.5192}, {"code": "2383", "name": "台光電", "shares": 102000, "amount": 92104543, "weight": 2.5035}, {"code": "2301", "name": "光寶科", "shares": 786000, "amount": 88031856, "weight": 2.3928}, {"code": "2360", "name": "致茂", "shares": 201000, "amount": 87936201, "weight": 2.3902}, {"code": "6213", "name": "聯茂", "shares": 936000, "amount": 82178518, "weight": 2.2337}, {"code": "6781", "name": "AES-KY", "shares": 74000, "amount": 81766466, "weight": 2.2225}, {"code": "2308", "name": "台達電", "shares": 183000, "amount": 78595141, "weight": 2.1363}, {"code": "2345", "name": "智邦", "shares": 97000, "amount": 74493022, "weight": 2.0248}, {"code": "6415", "name": "矽力*-KY", "shares": 207000, "amount": 72447480, "weight": 1.9692}, {"code": "6196", "name": "帆宣", "shares": 383000, "amount": 71428389, "weight": 1.9415}, {"code": "6510", "name": "精測", "shares": 86000, "amount": 71034732, "weight": 1.9308}, {"code": "3036", "name": "文曄", "shares": 537000, "amount": 70615323, "weight": 1.9194}, {"code": "3533", "name": "嘉澤", "shares": 51000, "amount": 68849388, "weight": 1.8714}, {"code": "2421", "name": "建準", "shares": 652000, "amount": 66829600, "weight": 1.8165}, {"code": "2059", "name": "川湖", "shares": 33000, "amount": 66494808, "weight": 1.8074}, {"code": "3033", "name": "威健", "shares": 1958000, "amount": 65983423, "weight": 1.7935}, {"code": "8114", "name": "振樺電", "shares": 227000, "amount": 65034233, "weight": 1.7677}, {"code": "6669", "name": "緯穎", "shares": 25000, "amount": 62249206, "weight": 1.692}, {"code": "3653", "name": "健策", "shares": 40000, "amount": 58798275, "weight": 1.5982}, {"code": "3706", "name": "神達", "shares": 800000, "amount": 56557745, "weight": 1.5373}, {"code": "6104", "name": "創惟", "shares": 356000, "amount": 55891840, "weight": 1.5192}, {"code": "6446", "name": "藥華藥", "shares": 90000, "amount": 51388706, "weight": 1.3968}, {"code": "2885", "name": "元大金", "shares": 1483000, "amount": 47823725, "weight": 1.2999}, {"code": "3044", "name": "健鼎", "shares": 180000, "amount": 44277139, "weight": 1.2035}, {"code": "2356", "name": "英業達", "shares": 917000, "amount": 40347934, "weight": 1.0967}, {"code": "3037", "name": "欣興", "shares": 322000, "amount": 36061862, "weight": 0.9802}, {"code": "1210", "name": "大成", "shares": 308000, "amount": 20389190, "weight": 0.5542}, {"code": "6138", "name": "茂達", "shares": 60000, "amount": 10827388, "weight": 0.2943}, {"code": "7722", "name": "LINEPAY", "shares": 5000, "amount": 3557623, "weight": 0.0967}, {"code": "2548", "name": "華固", "shares": 9000, "amount": 1019091, "weight": 0.0277}, {"code": "3491", "name": "昇達科", "shares": 1000, "amount": 338470, "weight": 0.0092}]}