{"date": "2025-12-02", "nav_total": 26866047333, "units": 2004436000, "nav_per_unit": 13.4, "n_holdings": 56, "holdings": [{"code": "2330", "name": "台積電", "shares": 1698000, "amount": 2428126491, "weight": 9.0379}, {"code": "6669", "name": "緯穎", "shares": 435000, "amount": 1948782475, "weight": 7.2537}, {"code": "3017", "name": "奇鋐", "shares": 1337000, "amount": 1758141003, "weight": 6.5441}, {"code": "5536", "name": "聖暉", "shares": 2258000, "amount": 1490259645, "weight": 5.547}, {"code": "2360", "name": "致茂", "shares": 1496000, "amount": 1163864036, "weight": 4.3321}, {"code": "2449", "name": "京元電子", "shares": 4100000, "amount": 928624926, "weight": 3.4565}, {"code": "2345", "name": "智邦", "shares": 883000, "amount": 927147293, "weight": 3.451}, {"code": "6805", "name": "富世達", "shares": 577000, "amount": 894343849, "weight": 3.3289}, {"code": "5439", "name": "高技", "shares": 2018000, "amount": 722428012, "weight": 2.689}, {"code": "2368", "name": "金像電", "shares": 1175000, "amount": 704991948, "weight": 2.6241}, {"code": "8210", "name": "勤誠", "shares": 769000, "amount": 691317129, "weight": 2.5732}, {"code": "2383", "name": "台光電", "shares": 480000, "amount": 691182799, "weight": 2.5727}, {"code": "2308", "name": "台達電", "shares": 691000, "amount": 683391646, "weight": 2.5437}, {"code": "3036", "name": "文曄", "shares": 4714000, "amount": 681161764, "weight": 2.5354}, {"code": "3665", "name": "貿聯-KY", "shares": 429136, "amount": 658701748, "weight": 2.4518}, {"code": "3231", "name": "緯創", "shares": 4486000, "amount": 641480612, "weight": 2.3877}, {"code": "6139", "name": "亞翔", "shares": 1444000, "amount": 634629770, "weight": 2.3622}, {"code": "3264", "name": "欣銓", "shares": 7078000, "amount": 612223486, "weight": 2.2788}, {"code": "6257", "name": "矽格", "shares": 6518000, "amount": 591160505, "weight": 2.2004}, {"code": "2441", "name": "超豐", "shares": 8375000, "amount": 590435122, "weight": 2.1977}, {"code": "2428", "name": "興勤", "shares": 3169000, "amount": 579903631, "weight": 2.1585}, {"code": "2059", "name": "川湖", "shares": 172000, "amount": 578775257, "weight": 2.1543}, {"code": "2421", "name": "建準", "shares": 3476000, "amount": 561366059, "weight": 2.0895}, {"code": "2451", "name": "創見", "shares": 2977000, "amount": 525419287, "weight": 1.9557}, {"code": "2316", "name": "楠梓電", "shares": 4320000, "amount": 473030495, "weight": 1.7607}, {"code": "2472", "name": "立隆電", "shares": 3985000, "amount": 406456430, "weight": 1.5129}, {"code": "2317", "name": "鴻海", "shares": 1783000, "amount": 395817475, "weight": 1.4733}, {"code": "6274", "name": "台燿", "shares": 924000, "amount": 380665024, "weight": 1.4169}, {"code": "3491", "name": "昇達科", "shares": 547000, "amount": 284430843, "weight": 1.0587}, {"code": "2404", "name": "漢唐", "shares": 364000, "amount": 282093496, "weight": 1.05}, {"code": "3706", "name": "神達", "shares": 3000400, "amount": 265812672, "weight": 0.9894}, {"code": "8299", "name": "群聯", "shares": 220000, "amount": 235373440, "weight": 0.8761}, {"code": "3443", "name": "創意", "shares": 99000, "amount": 214820914, "weight": 0.7996}, {"code": "4958", "name": "臻鼎-KY", "shares": 1434000, "amount": 209340240, "weight": 0.7792}, {"code": "2481", "name": "強茂", "shares": 2062000, "amount": 178551750, "weight": 0.6646}, {"code": "8358", "name": "金居", "shares": 781000, "amount": 177262180, "weight": 0.6598}, {"code": "3711", "name": "日月光投控", "shares": 706000, "amount": 161303748, "weight": 0.6004}, {"code": "3260", "name": "威剛", "shares": 800000, "amount": 140778088, "weight": 0.524}, {"code": "6177", "name": "達麗", "shares": 2994350, "amount": 140428829, "weight": 0.5227}, {"code": "5289", "name": "宜鼎", "shares": 282000, "amount": 128715232, "weight": 0.4791}, {"code": "3324", "name": "雙鴻", "shares": 109000, "amount": 96019253, "weight": 0.3574}, {"code": "2327", "name": "國巨", "shares": 380000, "amount": 86428074, "weight": 0.3217}, {"code": "1785", "name": "光洋科", "shares": 1481000, "amount": 85595226, "weight": 0.3186}, {"code": "9938", "name": "百和", "shares": 1461000, "amount": 82532497, "weight": 0.3072}, {"code": "8996", "name": "高力", "shares": 146000, "amount": 77669742, "weight": 0.2891}, {"code": "6446", "name": "藥華藥", "shares": 132583, "amount": 68669616, "weight": 0.2556}, {"code": "8464", "name": "億豐", "shares": 144000, "amount": 54564942, "weight": 0.2031}, {"code": "6472", "name": "保瑞", "shares": 100000, "amount": 52899247, "weight": 0.1969}, {"code": "2885", "name": "元大金", "shares": 1117420, "amount": 40836391, "weight": 0.152}, {"code": "3529", "name": "力旺", "shares": 15000, "amount": 30734758, "weight": 0.1144}, {"code": "4441", "name": "振大環球", "shares": 60000, "amount": 16065896, "weight": 0.0598}, {"code": "2548", "name": "華固", "shares": 29600, "amount": 2982131, "weight": 0.0111}, {"code": "7722", "name": "LINEPAY", "shares": 1000, "amount": 564186, "weight": 0.0021}, {"code": "1519", "name": "華城", "shares": 600, "amount": 402990, "weight": 0.0015}, {"code": "2886", "name": "兆豐金", "shares": 1000, "amount": 26866, "weight": 0.0001}, {"code": "2881", "name": "富邦金", "shares": 250, "amount": 0, "weight": 0.0}]}