{"date": "2025-06-03", "nav_total": 2097729547, "units": 196730000, "nav_per_unit": 10.66, "n_holdings": 51, "holdings": [{"code": "2454", "name": "聯發科技", "shares": 89000, "amount": 113487168, "weight": 5.41}, {"code": "2330", "name": "台灣積體電路製造", "shares": 116000, "amount": 110130801, "weight": 5.25}, {"code": "2317", "name": "鴻海精密工業", "shares": 719000, "amount": 108872163, "weight": 5.19}, {"code": "2357", "name": "華碩電腦", "shares": 149000, "amount": 95027148, "weight": 4.53}, {"code": "2881", "name": "富邦金融控股", "shares": 985000, "amount": 82440771, "weight": 3.93}, {"code": "8016", "name": "矽創電子", "shares": 319000, "amount": 69434848, "weight": 3.31}, {"code": "3044", "name": "健鼎科技", "shares": 335000, "amount": 69225075, "weight": 3.3}, {"code": "2382", "name": "廣達電腦", "shares": 250000, "amount": 68805529, "weight": 3.28}, {"code": "2308", "name": "台達電子工業", "shares": 176000, "amount": 66707799, "weight": 3.18}, {"code": "6121", "name": "新普科技", "shares": 171000, "amount": 65658934, "weight": 3.13}, {"code": "2891", "name": "中國信託金融控股", "shares": 1502000, "amount": 64610070, "weight": 3.08}, {"code": "4915", "name": "致伸科技", "shares": 769000, "amount": 58526654, "weight": 2.79}, {"code": "5904", "name": "寶雅國際", "shares": 113000, "amount": 58316881, "weight": 2.78}, {"code": "5434", "name": "崇越科技", "shares": 225000, "amount": 57897335, "weight": 2.76}, {"code": "3702", "name": "大聯大控股", "shares": 892000, "amount": 57897335, "weight": 2.76}, {"code": "2393", "name": "億光電子工業", "shares": 686000, "amount": 53072557, "weight": 2.53}, {"code": "2345", "name": "智邦科技", "shares": 54000, "amount": 39017769, "weight": 1.86}, {"code": "2383", "name": "台光電子材料", "shares": 48000, "amount": 37549358, "weight": 1.79}, {"code": "6669", "name": "緯穎科技服務", "shares": 15000, "amount": 37129812, "weight": 1.77}, {"code": "3131", "name": "弘塑科技", "shares": 26000, "amount": 32095262, "weight": 1.53}, {"code": "3293", "name": "鈊象電子", "shares": 38000, "amount": 31675716, "weight": 1.51}, {"code": "2379", "name": "瑞昱半導體", "shares": 56000, "amount": 30417078, "weight": 1.45}, {"code": "2059", "name": "川湖科技", "shares": 13000, "amount": 28109575, "weight": 1.34}, {"code": "3665", "name": "貿聯控股（BizLink Holding In", "shares": 43000, "amount": 27899802, "weight": 1.33}, {"code": "3653", "name": "健策精密工業", "shares": 20000, "amount": 27690030, "weight": 1.32}, {"code": "2360", "name": "致茂電子", "shares": 68000, "amount": 23284797, "weight": 1.11}, {"code": "6442", "name": "光紅建聖", "shares": 54000, "amount": 22445706, "weight": 1.07}, {"code": "3017", "name": "奇鋐科技", "shares": 32000, "amount": 21187068, "weight": 1.01}, {"code": "2610", "name": "中華航空", "shares": 940000, "amount": 20977295, "weight": 1.0}, {"code": "1319", "name": "東陽實業廠", "shares": 145000, "amount": 19299111, "weight": 0.92}, {"code": "3529", "name": "力旺電子", "shares": 9000, "amount": 19299111, "weight": 0.92}, {"code": "6757", "name": "台灣虎航", "shares": 207000, "amount": 19299111, "weight": 0.92}, {"code": "6223", "name": "旺矽科技", "shares": 24000, "amount": 18669792, "weight": 0.89}, {"code": "3227", "name": "原相科技", "shares": 82000, "amount": 18040474, "weight": 0.86}, {"code": "6670", "name": "復盛應用科技", "shares": 53000, "amount": 17830701, "weight": 0.85}, {"code": "9907", "name": "統一實業", "shares": 869000, "amount": 17620928, "weight": 0.84}, {"code": "6446", "name": "藥華醫藥", "shares": 34000, "amount": 17411155, "weight": 0.83}, {"code": "3450", "name": "聯鈞光電", "shares": 97000, "amount": 17411155, "weight": 0.83}, {"code": "3211", "name": "順達科技", "shares": 77000, "amount": 16152517, "weight": 0.77}, {"code": "8028", "name": "昇陽國際半導體", "shares": 116000, "amount": 15523198, "weight": 0.74}, {"code": "8039", "name": "台虹科技", "shares": 324000, "amount": 15103652, "weight": 0.72}, {"code": "3491", "name": "昇達科技", "shares": 47000, "amount": 14684106, "weight": 0.7}, {"code": "3526", "name": "凡甲科技", "shares": 60000, "amount": 13425469, "weight": 0.64}, {"code": "6561", "name": "是方電訊", "shares": 32000, "amount": 13425469, "weight": 0.64}, {"code": "8114", "name": "振樺電子", "shares": 43000, "amount": 13215696, "weight": 0.63}, {"code": "6274", "name": "台燿科技", "shares": 67000, "amount": 12586377, "weight": 0.6}, {"code": "5234", "name": "達興材料", "shares": 44000, "amount": 10069101, "weight": 0.48}, {"code": "3714", "name": "富采投資控股", "shares": 264000, "amount": 8810464, "weight": 0.42}, {"code": "6811", "name": "宏碁資訊服務", "shares": 38000, "amount": 8810464, "weight": 0.42}, {"code": "3605", "name": "宏致電子", "shares": 170000, "amount": 8600691, "weight": 0.41}, {"code": "2723", "name": "開曼美食達人", "shares": 72000, "amount": 6502961, "weight": 0.31}]}