{"date": "2025-09-22", "nav_total": 4507881564, "units": 333230000, "nav_per_unit": 13.53, "n_holdings": 48, "holdings": [{"code": "2330", "name": "台灣積體電路製造", "shares": 297000, "amount": 375506534, "weight": 8.33}, {"code": "2317", "name": "鴻海精密工業", "shares": 1255000, "amount": 268669741, "weight": 5.96}, {"code": "2308", "name": "台達電子工業", "shares": 249000, "amount": 221336984, "weight": 4.91}, {"code": "2454", "name": "聯發科技", "shares": 140000, "amount": 201502305, "weight": 4.47}, {"code": "2383", "name": "台光電子材料", "shares": 113000, "amount": 145604574, "weight": 3.23}, {"code": "2345", "name": "智邦科技", "shares": 138000, "amount": 140195116, "weight": 3.11}, {"code": "2382", "name": "廣達電腦", "shares": 473000, "amount": 132982506, "weight": 2.95}, {"code": "6669", "name": "緯穎科技服務", "shares": 40000, "amount": 129376200, "weight": 2.87}, {"code": "2881", "name": "富邦金融控股", "shares": 1387000, "amount": 121712802, "weight": 2.7}, {"code": "2891", "name": "中國信託金融控股", "shares": 2759000, "amount": 120360437, "weight": 2.67}, {"code": "2884", "name": "玉山金融控股", "shares": 3306622, "amount": 110893886, "weight": 2.46}, {"code": "2360", "name": "致茂電子", "shares": 159000, "amount": 95116301, "weight": 2.11}, {"code": "2368", "name": "金像電子（股）公司", "shares": 216000, "amount": 94214724, "weight": 2.09}, {"code": "9802", "name": "鈺齊國際", "shares": 902000, "amount": 94214724, "weight": 2.09}, {"code": "3665", "name": "貿聯控股（BizLink Holding In", "shares": 82336, "amount": 91960783, "weight": 2.04}, {"code": "2357", "name": "華碩電腦", "shares": 121000, "amount": 80691079, "weight": 1.79}, {"code": "3017", "name": "奇鋐科技", "shares": 77000, "amount": 80240291, "weight": 1.78}, {"code": "2376", "name": "技嘉科技", "shares": 283000, "amount": 79789503, "weight": 1.77}, {"code": "3653", "name": "健策精密工業", "shares": 34000, "amount": 78437139, "weight": 1.74}, {"code": "2059", "name": "川湖科技", "shares": 23000, "amount": 76633986, "weight": 1.7}, {"code": "6223", "name": "旺矽科技", "shares": 46000, "amount": 73478469, "weight": 1.63}, {"code": "6757", "name": "台灣虎航", "shares": 882000, "amount": 69421376, "weight": 1.54}, {"code": "5234", "name": "達興材料", "shares": 174000, "amount": 66265858, "weight": 1.47}, {"code": "2379", "name": "瑞昱半導體", "shares": 109000, "amount": 59504036, "weight": 1.32}, {"code": "3293", "name": "鈊象電子", "shares": 69000, "amount": 56348519, "weight": 1.25}, {"code": "8016", "name": "矽創電子", "shares": 257000, "amount": 56348519, "weight": 1.25}, {"code": "3044", "name": "健鼎科技", "shares": 183000, "amount": 55446943, "weight": 1.23}, {"code": "1519", "name": "華城電機", "shares": 90000, "amount": 53193002, "weight": 1.18}, {"code": "6510", "name": "中華精測科技", "shares": 33000, "amount": 52291426, "weight": 1.16}, {"code": "5904", "name": "寶雅國際", "shares": 108450, "amount": 50037485, "weight": 1.11}, {"code": "5434", "name": "崇越科技", "shares": 158000, "amount": 46881968, "weight": 1.04}, {"code": "5439", "name": "高技企業", "shares": 140000, "amount": 45980391, "weight": 1.02}, {"code": "6811", "name": "宏碁資訊服務", "shares": 177000, "amount": 44177239, "weight": 0.98}, {"code": "6213", "name": "聯茂電子", "shares": 379000, "amount": 41923298, "weight": 0.93}, {"code": "6274", "name": "台燿科技", "shares": 132000, "amount": 38767781, "weight": 0.86}, {"code": "6442", "name": "光紅建聖", "shares": 44000, "amount": 35612264, "weight": 0.79}, {"code": "3526", "name": "凡甲科技", "shares": 140000, "amount": 35612264, "weight": 0.79}, {"code": "6121", "name": "新普科技", "shares": 93000, "amount": 34259899, "weight": 0.76}, {"code": "8114", "name": "振樺電子", "shares": 148000, "amount": 34259899, "weight": 0.76}, {"code": "6561", "name": "是方電訊", "shares": 73000, "amount": 31555170, "weight": 0.7}, {"code": "2610", "name": "中華航空", "shares": 1417000, "amount": 29752018, "weight": 0.66}, {"code": "3605", "name": "宏致電子", "shares": 399000, "amount": 29301230, "weight": 0.65}, {"code": "3211", "name": "順達科技", "shares": 77000, "amount": 27047289, "weight": 0.6}, {"code": "4915", "name": "致伸科技", "shares": 251000, "amount": 19834678, "weight": 0.44}, {"code": "3529", "name": "力旺電子", "shares": 8000, "amount": 16679161, "weight": 0.37}, {"code": "1319", "name": "東陽實業廠", "shares": 173000, "amount": 16679161, "weight": 0.37}, {"code": "6670", "name": "復盛應用科技", "shares": 63000, "amount": 16679161, "weight": 0.37}, {"code": "2723", "name": "開曼美食達人", "shares": 125000, "amount": 9466551, "weight": 0.21}]}