{"date": "2026-04-07", "nav_total": 1517234175, "units": 120690000, "nav_per_unit": 12.57, "n_holdings": 35, "holdings": [{"code": "2330", "name": "台積電", "shares": 149999, "amount": 278867641, "weight": 18.38}, {"code": "2383", "name": "台光電", "shares": 32000, "amount": 92247837, "weight": 6.08}, {"code": "2345", "name": "智邦", "shares": 56000, "amount": 90427156, "weight": 5.96}, {"code": "6223", "name": "旺矽", "shares": 22000, "amount": 86178901, "weight": 5.68}, {"code": "3017", "name": "奇鋐", "shares": 41500, "amount": 84206496, "weight": 5.55}, {"code": "3037", "name": "欣興", "shares": 142001, "amount": 80109964, "weight": 5.28}, {"code": "2308", "name": "台達電", "shares": 45499, "amount": 68882431, "weight": 4.54}, {"code": "3653", "name": "健策", "shares": 18000, "amount": 67668644, "weight": 4.46}, {"code": "6274", "name": "台燿", "shares": 89000, "amount": 60841090, "weight": 4.01}, {"code": "3665", "name": "貿聯-KY", "shares": 30000, "amount": 59627303, "weight": 3.93}, {"code": "6515", "name": "穎崴", "shares": 8100, "amount": 57503175, "weight": 3.79}, {"code": "2368", "name": "金像電", "shares": 60000, "amount": 55682494, "weight": 3.67}, {"code": "2360", "name": "致茂", "shares": 34000, "amount": 53406642, "weight": 3.52}, {"code": "5274", "name": "信驊", "shares": 4600, "amount": 52799749, "weight": 3.48}, {"code": "8046", "name": "南電", "shares": 74000, "amount": 46123918, "weight": 3.04}, {"code": "2313", "name": "華通", "shares": 125000, "amount": 34441215, "weight": 2.27}, {"code": "6805", "name": "富世達", "shares": 18001, "amount": 33227428, "weight": 2.19}, {"code": "6442", "name": "光聖", "shares": 13000, "amount": 27310215, "weight": 1.8}, {"code": "2449", "name": "京元電子", "shares": 100000, "amount": 26855044, "weight": 1.77}, {"code": "3711", "name": "日月光投控", "shares": 74000, "amount": 26096427, "weight": 1.72}, {"code": "2467", "name": "志聖", "shares": 59000, "amount": 24124023, "weight": 1.59}, {"code": "3105", "name": "穩懋", "shares": 56000, "amount": 22758512, "weight": 1.5}, {"code": "6510", "name": "精測", "shares": 5000, "amount": 16689575, "weight": 1.1}, {"code": "6257", "name": "矽格", "shares": 95000, "amount": 14717171, "weight": 0.97}, {"code": "4979", "name": "華星光", "shares": 36000, "amount": 14565448, "weight": 0.96}, {"code": "3491", "name": "昇達科", "shares": 5000, "amount": 8193064, "weight": 0.54}, {"code": "3081", "name": "聯亞", "shares": 4000, "amount": 8041341, "weight": 0.53}, {"code": "5536", "name": "聖暉", "shares": 7000, "amount": 4855149, "weight": 0.32}, {"code": "6239", "name": "力成", "shares": 25000, "amount": 4855149, "weight": 0.32}, {"code": "2481", "name": "強茂", "shares": 45000, "amount": 4703425, "weight": 0.31}, {"code": "3260", "name": "威剛", "shares": 1000, "amount": 303446, "weight": 0.02}, {"code": "3443", "name": "創意", "shares": 50, "amount": 151723, "weight": 0.01}, {"code": "4904", "name": "遠傳", "shares": 3, "amount": 0, "weight": 0.0}, {"code": "3045", "name": "台灣大", "shares": 1, "amount": 0, "weight": 0.0}, {"code": "2412", "name": "中華電", "shares": 1, "amount": 0, "weight": 0.0}]}