{"date": "2026-02-05", "nav_total": 21332804952, "units": 1932522000, "nav_per_unit": 11.04, "n_holdings": 49, "holdings": [{"code": "LITE US", "name": "LUMENTUM HOLDINGS INC", "shares": 87752, "amount": 1401565285, "weight": 6.57}, {"code": "GOOGL US", "name": "ALPHABET INC-CL A", "shares": 123700, "amount": 1297034541, "weight": 6.08}, {"code": "NVDA US", "name": "NVIDIA CORP", "shares": 227550, "amount": 1239435967, "weight": 5.81}, {"code": "2330", "name": "台積電", "shares": 686000, "amount": 1211703321, "weight": 5.68}, {"code": "SNDK US", "name": "SANDISK CORP", "shares": 62333, "amount": 1137038503, "weight": 5.33}, {"code": "MU US", "name": "MICRON TECHNOLOGY INC", "shares": 88871, "amount": 1077306650, "weight": 5.05}, {"code": "AVGO US", "name": "BROADCOM INC", "shares": 104182, "amount": 1023974637, "weight": 4.8}, {"code": "TER US", "name": "TERADYNE INC", "shares": 92600, "amount": 795713624, "weight": 3.73}, {"code": "2308", "name": "台達電", "shares": 628000, "amount": 723182087, "weight": 3.39}, {"code": "TSEM US", "name": "TOWER SEMICONDUCTOR LTD", "shares": 177049, "amount": 723182087, "weight": 3.39}, {"code": "ASML NA", "name": "ASML HOLDING NV", "shares": 15852, "amount": 680516477, "weight": 3.19}, {"code": "WDC US", "name": "WESTERN DIGITAL CORP", "shares": 57762, "amount": 475721550, "weight": 2.23}, {"code": "5706 JP", "name": "MITSUI KINZOKU CO LTD", "shares": 111500, "amount": 473588269, "weight": 2.22}, {"code": "COHR US", "name": "COHERENT CORP", "shares": 66000, "amount": 437322501, "weight": 2.05}, {"code": "ENR GR", "name": "SIEMENS ENERGY AG", "shares": 78915, "amount": 435189221, "weight": 2.04}, {"code": "005930 KP", "name": "SAMSUNG ELECTRONICS CO LTD", "shares": 125753, "amount": 433055940, "weight": 2.03}, {"code": "GEV US", "name": "GE VERNOVA INC", "shares": 18000, "amount": 420256257, "weight": 1.97}, {"code": "CIEN US", "name": "CIENA CORP", "shares": 50027, "amount": 401056733, "weight": 1.88}, {"code": "AMAT US", "name": "APPLIED MATERIALS INC", "shares": 41100, "amount": 394656891, "weight": 1.85}, {"code": "SMTC US", "name": "SEMTECH CORP", "shares": 137600, "amount": 362657684, "weight": 1.7}, {"code": "BE US", "name": "BLOOM ENERGY CORP- A", "shares": 71100, "amount": 307192391, "weight": 1.44}, {"code": "6590 JP", "name": "SHIBAURA MECHATRONICS CORP", "shares": 49900, "amount": 281593025, "weight": 1.32}, {"code": "034020 KP", "name": "DOOSAN ENERBILITY CO LTD", "shares": 124987, "amount": 245327256, "weight": 1.15}, {"code": "4062 JP", "name": "IBIDEN CO LTD", "shares": 169400, "amount": 243193976, "weight": 1.14}, {"code": "6146 JP", "name": "DISCO CORP", "shares": 17000, "amount": 223994451, "weight": 1.05}, {"code": "KEYS US", "name": "KEYSIGHT TECHNOLOGIES IN", "shares": 31300, "amount": 219727891, "weight": 1.03}, {"code": "LMT US", "name": "LOCKHEED MARTIN CORP", "shares": 10982, "amount": 211194769, "weight": 0.99}, {"code": "2449", "name": "京元電子", "shares": 746000, "amount": 209061488, "weight": 0.98}, {"code": "6274", "name": "台燿", "shares": 399000, "amount": 206928208, "weight": 0.97}, {"code": "3653", "name": "健策", "shares": 60000, "amount": 179195561, "weight": 0.84}, {"code": "MP US", "name": "MP MATERIALS CORP", "shares": 99800, "amount": 179195561, "weight": 0.84}, {"code": "RHM GR", "name": "RHEINMETALL AG", "shares": 2982, "amount": 177062281, "weight": 0.83}, {"code": "000660 KP", "name": "SK HYNIX INC", "shares": 9602, "amount": 174929000, "weight": 0.82}, {"code": "FCX US", "name": "FREEPORT-MCMORAN INC", "shares": 91900, "amount": 172795720, "weight": 0.81}, {"code": "7729 JP", "name": "TOKYO SEIMITSU CO LTD", "shares": 62100, "amount": 170662439, "weight": 0.8}, {"code": "285A JP", "name": "KIOXIA HOLDINGS CORP", "shares": 38400, "amount": 151462915, "weight": 0.71}, {"code": "MKSI US", "name": "MKS INC", "shares": 20900, "amount": 149329634, "weight": 0.7}, {"code": "2383", "name": "台光電", "shares": 74000, "amount": 145063073, "weight": 0.68}, {"code": "2454", "name": "聯發科", "shares": 82000, "amount": 145063073, "weight": 0.68}, {"code": "KTOS US", "name": "KRATOS DEFENSE & SECURITY", "shares": 54100, "amount": 145063073, "weight": 0.68}, {"code": "6315 JP", "name": "TOWA CORP", "shares": 237600, "amount": 142929793, "weight": 0.67}, {"code": "012450 KP", "name": "HANWHA AEROSPACE CO LTD", "shares": 5155, "amount": 136529951, "weight": 0.64}, {"code": "CAT US", "name": "CATERPILLAR INC", "shares": 6360, "amount": 136529951, "weight": 0.64}, {"code": "2313", "name": "華通", "shares": 708000, "amount": 123730268, "weight": 0.58}, {"code": "2368", "name": "金像電", "shares": 143000, "amount": 108797305, "weight": 0.51}, {"code": "2360", "name": "致茂", "shares": 103000, "amount": 100264183, "weight": 0.47}, {"code": "CAMT US", "name": "CAMTEK LTD", "shares": 22200, "amount": 100264183, "weight": 0.47}, {"code": "AIXA GR", "name": "AIXTRON SE", "shares": 85721, "amount": 63998414, "weight": 0.3}, {"code": "RKLB US", "name": "ROCKET LAB CORP", "shares": 15100, "amount": 31999207, "weight": 0.15}]}