{"date": "2026-01-21", "nav_total": 8405931188, "units": 757437000, "nav_per_unit": 11.1, "n_holdings": 37, "holdings": [{"code": "MU US", "name": "MICRON TECHNOLOGY INC", "shares": 58000, "amount": 669112122, "weight": 7.96}, {"code": "GOOGL US", "name": "ALPHABET INC-CL A(Alphabet公司)", "shares": 52000, "amount": 528733071, "weight": 6.29}, {"code": "LITE US", "name": "LUMENTUM HOLDINGS INC.lite us", "shares": 37500, "amount": 422818338, "weight": 5.03}, {"code": "AVGO US", "name": "BROADCOM LTD", "shares": 36000, "amount": 378266903, "weight": 4.5}, {"code": "SNDK US", "name": "SANDISK CORP", "shares": 23000, "amount": 329512502, "weight": 3.92}, {"code": "NVDA US", "name": "NVIDIA CORP(輝達公司)", "shares": 58500, "amount": 328671909, "weight": 3.91}, {"code": "ENR GY", "name": "SIEMENS ENERGY AG", "shares": 64000, "amount": 312700640, "weight": 3.72}, {"code": "RHM GY", "name": "RHEINMETALL AG", "shares": 4450, "amount": 312700640, "weight": 3.72}, {"code": "2330", "name": "台積電", "shares": 165000, "amount": 292526405, "weight": 3.48}, {"code": "300308 CH", "name": "ZHONGJI INNOLIGHT CO LTD-A", "shares": 105000, "amount": 279076915, "weight": 3.32}, {"code": "2308", "name": "台達電", "shares": 240000, "amount": 271511577, "weight": 3.23}, {"code": "KTOS US", "name": "KRATOS DEFENSE & SECURITY", "shares": 65000, "amount": 263946239, "weight": 3.14}, {"code": "HOT GY", "name": "HOCHTIEF AG", "shares": 20000, "amount": 259743273, "weight": 3.09}, {"code": "CIEN US", "name": "CIENA CORP", "shares": 32000, "amount": 243772004, "weight": 2.9}, {"code": "CCJ US", "name": "CAMECO CORP", "shares": 66000, "amount": 241250225, "weight": 2.87}, {"code": "GEV US", "name": "GE VERNOVA INC", "shares": 11000, "amount": 237887852, "weight": 2.83}, {"code": "TER US", "name": "TERADYNE INC", "shares": 33500, "amount": 237047259, "weight": 2.82}, {"code": "5706 JP", "name": "Mitsui Mining ＆ Smelting Co", "shares": 50000, "amount": 219394804, "weight": 2.61}, {"code": "BE US", "name": "BLOOM ENERGY CORP- A", "shares": 40000, "amount": 191655231, "weight": 2.28}, {"code": "7769", "name": "鴻勁", "shares": 50000, "amount": 174843368, "weight": 2.08}, {"code": "6590 JP", "name": "SHIBAURA MECHATRONICS CORP", "shares": 34000, "amount": 168959216, "weight": 2.01}, {"code": "COHR US", "name": "COHERENT INC", "shares": 27000, "amount": 164756251, "weight": 1.96}, {"code": "3017", "name": "奇鋐", "shares": 125000, "amount": 162234471, "weight": 1.93}, {"code": "AMD US", "name": "ADVANCED MICRO DEVICES.amd us(超微半導體公司)", "shares": 18000, "amount": 131973119, "weight": 1.57}, {"code": "4062 JP", "name": "IBIDEN CO LTD", "shares": 80000, "amount": 126929560, "weight": 1.51}, {"code": "ASML US", "name": "ASML HOLDING NV-NY REG SHS", "shares": 3000, "amount": 126088967, "weight": 1.5}, {"code": "KLAC US", "name": "KLA CORP", "shares": 2500, "amount": 117683036, "weight": 1.4}, {"code": "WDC US", "name": "WESTERN DIGITAL CORP", "shares": 16500, "amount": 116001850, "weight": 1.38}, {"code": "3665", "name": "貿聯-KY", "shares": 80000, "amount": 107595919, "weight": 1.28}, {"code": "BA/ LN", "name": "BAE SYSTEMS PLC", "shares": 100000, "amount": 87421684, "weight": 1.04}, {"code": "RR/ LN", "name": "ROLLS-ROYCE HOLDINGS PLC", "shares": 160000, "amount": 86581091, "weight": 1.03}, {"code": "6857 JP", "name": "ADVANTEST CORP", "shares": 20000, "amount": 85740498, "weight": 1.02}, {"code": "HOOD US", "name": "ROBINHOOD MARKETS INC - A", "shares": 25000, "amount": 83218718, "weight": 0.99}, {"code": "5016 JP", "name": "JX ADVANCED METALS CORP", "shares": 150000, "amount": 79856346, "weight": 0.95}, {"code": "6954 JP", "name": "Fanuc LTD", "shares": 57500, "amount": 74812787, "weight": 0.89}, {"code": "6525 JP", "name": "KOKUSAI ELECTRIC CORP", "shares": 60000, "amount": 73131601, "weight": 0.87}, {"code": "8210", "name": "勤誠", "shares": 81000, "amount": 73131601, "weight": 0.87}]}